Workbook

Sheet Budget Summary
B2: HEARTH · Production Budget Template
B4: Project Title: | C4: Director: | D4: Producer: | E4: Date: | F4: Version:
B7: Budget Category | C7: Budgeted ($) | D7: Actual ($) | E7: Variance ($) | F7: Notes
B8: Above the Line | C8: ='Above the Line'!C27 -> 0 | E8: =C8-D8 -> 0
B9: Production Crew | C9: ='Production Crew'!C22 -> 0 | E9: =C9-D9 -> 0
B10: Equipment & Facilities | C10: =Equipment!C18 -> 0 | E10: =C10-D10 -> 0
B11: Art Department | C11: ='Art Department'!C14 -> 0 | E11: =C11-D11 -> 0
B12: Locations & Transport | C12: =Locations!C14 -> 0 | E12: =C12-D12 -> 0
B13: Post-Production | C13: ='Post Production'!C16 -> 0 | E13: =C13-D13 -> 0
B14: Music | C14: =Music!C10 -> 0 | E14: =C14-D14 -> 0
B15: Other & Insurance | C15: =Other!C14 -> 0 | E15: =C15-D15 -> 0
B16: SUBTOTAL | C16: =SUM(C8:C15) -> 0 | D16: =SUM(D8:D15) -> 0 | E16: =C16-D16 -> 0
B17: Contingency (10% recommended) | C17: =C16*0.1 -> 0 | E17: =C17-D17 -> 0
B18: TOTAL BUDGET | C18: =C16+C17 -> 0 | D18: =D16+D17 -> 0 | E18: =C18-D18 -> 0
B20: COLOR KEY: | D20: Blue cells = your inputs
D21: White/warm cells = calculated automatically
A23: HEARTH · Production Resource Library · buildyourhearth.studio

Sheet Above the Line
B2: HEARTH · Above the Line
B4: Line Item | C4: Rate ($) | D4: # Units | E4: # Days | F4: Total ($) | G4: Notes
B5: STORY & RIGHTS
B6: Script / Story Rights | F6: =IF(C6="","",C6*D6*E6)
B7: Screenplay Fee | F7: =IF(C7="","",C7*D7*E7)
B8: Script Revision Fee | F8: =IF(C8="","",C8*D8*E8)
B9: DIRECTION & PRODUCING
B10: Director Fee | F10: =IF(C10="","",C10*D10*E10)
B11: Producer Fee | F11: =IF(C11="","",C11*D11*E11)
B12: Executive Producer Fee | F12: =IF(C12="","",C12*D12*E12)
B13: Line Producer Fee | F13: =IF(C13="","",C13*D13*E13)
B14: PRINCIPAL CAST
B15: Lead Actor 1 | F15: =IF(C15="","",C15*D15*E15)
B16: Lead Actor 2 | F16: =IF(C16="","",C16*D16*E16)
B17: Supporting Actor 1 | F17: =IF(C17="","",C17*D17*E17)
B18: Supporting Actor 2 | F18: =IF(C18="","",C18*D18*E18)
B19: Supporting Actor 3 | F19: =IF(C19="","",C19*D19*E19)
B20: Day Player / Additional Cast | F20: =IF(C20="","",C20*D20*E20)
B21: Casting Director Fee | F21: =IF(C21="","",C21*D21*E21)
B22: Casting Expenses | F22: =IF(C22="","",C22*D22*E22)
B23: TOTAL — Above the Line | C23: =SUM(F5:F22) -> 0 | F23: =SUM(F5:F22) -> 0
B25: NOTE: Enter Rate, Units, and Days for each line item. Total calculates automatically.

Sheet Production Crew
B2: HEARTH · Production Crew
B4: Line Item | C4: Rate ($) | D4: # Units | E4: # Days | F4: Total ($) | G4: Notes
B5: CAMERA DEPARTMENT
B6: Director of Photography (DP) | F6: =IF(C6="","",C6*D6*E6)
B7: Camera Operator | F7: =IF(C7="","",C7*D7*E7)
B8: 1st AC / Focus Puller | F8: =IF(C8="","",C8*D8*E8)
B9: 2nd AC / Loader | F9: =IF(C9="","",C9*D9*E9)
B10: DIT (Digital Imaging Technician) | F10: =IF(C10="","",C10*D10*E10)
B11: LIGHTING / GRIP
B12: Gaffer | F12: =IF(C12="","",C12*D12*E12)
B13: Best Boy Electric | F13: =IF(C13="","",C13*D13*E13)
B14: Key Grip | F14: =IF(C14="","",C14*D14*E14)
B15: Best Boy Grip | F15: =IF(C15="","",C15*D15*E15)
B16: SOUND
B17: Sound Recordist / Mixer | F17: =IF(C17="","",C17*D17*E17)
B18: Boom Operator | F18: =IF(C18="","",C18*D18*E18)
B19: PRODUCTION
B20: 1st Assistant Director | F20: =IF(C20="","",C20*D20*E20)
B21: 2nd Assistant Director | F21: =IF(C21="","",C21*D21*E21)
B22: Production Coordinator | F22: =IF(C22="","",C22*D22*E22)
B23: Production Assistant (1) | F23: =IF(C23="","",C23*D23*E23)
B24: Production Assistant (2) | F24: =IF(C24="","",C24*D24*E24)
B25: TOTAL — Production Crew | C25: =SUM(F5:F24) -> 0 | F25: =SUM(F5:F24) -> 0
B27: NOTE: Enter Rate, Units, and Days for each line item. Total calculates automatically.

Sheet Equipment
B2: HEARTH · Equipment
B4: Line Item | C4: Rate ($) | D4: # Units | E4: # Days | F4: Total ($) | G4: Notes
B5: CAMERA
B6: Camera Body Rental | F6: =IF(C6="","",C6*D6*E6)
B7: Lens Package Rental | F7: =IF(C7="","",C7*D7*E7)
B8: Camera Accessories | F8: =IF(C8="","",C8*D8*E8)
B9: Monitors / On-Set Viewing | F9: =IF(C9="","",C9*D9*E9)
B10: LIGHTING
B11: Lighting Package Rental | F11: =IF(C11="","",C11*D11*E11)
B12: Generator Rental | F12: =IF(C12="","",C12*D12*E12)
B13: GRIP
B14: Grip Package Rental | F14: =IF(C14="","",C14*D14*E14)
B15: Expendables (tape, gels, etc.) | F15: =IF(C15="","",C15*D15*E15)
B16: SOUND
B17: Sound Package Rental | F17: =IF(C17="","",C17*D17*E17)
B18: Walkie Talkies / Comms | F18: =IF(C18="","",C18*D18*E18)
B19: OTHER
B20: Hard Drives / Storage | F20: =IF(C20="","",C20*D20*E20)
B21: Miscellaneous Equipment | F21: =IF(C21="","",C21*D21*E21)
B22: TOTAL — Equipment | C22: =SUM(F5:F21) -> 0 | F22: =SUM(F5:F21) -> 0
B24: NOTE: Enter Rate, Units, and Days for each line item. Total calculates automatically.

Sheet Art Department
B2: HEARTH · Art Department
B4: Line Item | C4: Rate ($) | D4: # Units | E4: # Days | F4: Total ($) | G4: Notes
B5: PERSONNEL
B6: Production Designer | F6: =IF(C6="","",C6*D6*E6)
B7: Art Director | F7: =IF(C7="","",C7*D7*E7)
B8: Set Decorator | F8: =IF(C8="","",C8*D8*E8)
B9: Props Master | F9: =IF(C9="","",C9*D9*E9)
B10: Wardrobe Stylist | F10: =IF(C10="","",C10*D10*E10)
B11: Hair & Makeup Artist | F11: =IF(C11="","",C11*D11*E11)
B12: MATERIALS & PURCHASES
B13: Props Purchase / Rental | F13: =IF(C13="","",C13*D13*E13)
B14: Set Dressing / Decor | F14: =IF(C14="","",C14*D14*E14)
B15: Wardrobe / Costume | F15: =IF(C15="","",C15*D15*E15)
B16: Hair & Makeup Supplies | F16: =IF(C16="","",C16*D16*E16)
B17: TOTAL — Art Department | C17: =SUM(F5:F16) -> 0 | F17: =SUM(F5:F16) -> 0
B19: NOTE: Enter Rate, Units, and Days for each line item. Total calculates automatically.

Sheet Locations
B2: HEARTH · Locations
B4: Line Item | C4: Rate ($) | D4: # Units | E4: # Days | F4: Total ($) | G4: Notes
B5: LOCATION FEES
B6: Location 1 Fee | F6: =IF(C6="","",C6*D6*E6)
B7: Location 2 Fee | F7: =IF(C7="","",C7*D7*E7)
B8: Location 3 Fee | F8: =IF(C8="","",C8*D8*E8)
B9: Location Cleaning Deposits | F9: =IF(C9="","",C9*D9*E9)
B10: Location Permits | F10: =IF(C10="","",C10*D10*E10)
B11: TRANSPORT
B12: Production Vehicle Rental | F12: =IF(C12="","",C12*D12*E12)
B13: Mileage / Fuel | F13: =IF(C13="","",C13*D13*E13)
B14: Parking | F14: =IF(C14="","",C14*D14*E14)
B15: Equipment Transport | F15: =IF(C15="","",C15*D15*E15)
B16: CATERING
B17: Craft Services (per person/day) | F17: =IF(C17="","",C17*D17*E17)
B18: Meal Buyouts | F18: =IF(C18="","",C18*D18*E18)
B19: TOTAL — Locations | C19: =SUM(F5:F18) -> 0 | F19: =SUM(F5:F18) -> 0
B21: NOTE: Enter Rate, Units, and Days for each line item. Total calculates automatically.

Sheet Post Production
B2: HEARTH · Post Production
B4: Line Item | C4: Rate ($) | D4: # Units | E4: # Days | F4: Total ($) | G4: Notes
B5: EDITORIAL
B6: Editor Fee | F6: =IF(C6="","",C6*D6*E6)
B7: Assistant Editor Fee | F7: =IF(C7="","",C7*D7*E7)
B8: Editing Software / License | F8: =IF(C8="","",C8*D8*E8)
B9: COLOR & SOUND
B10: Color Grade | F10: =IF(C10="","",C10*D10*E10)
B11: Sound Mix & Design | F11: =IF(C11="","",C11*D11*E11)
B12: Music Score / Composer | F12: =IF(C12="","",C12*D12*E12)
B13: ADR (Additional Dialogue) | F13: =IF(C13="","",C13*D13*E13)
B14: DELIVERY
B15: Visual Effects (VFX) | F15: =IF(C15="","",C15*D15*E15)
B16: Titles & Graphics | F16: =IF(C16="","",C16*D16*E16)
B17: Closed Captions / Subtitles | F17: =IF(C17="","",C17*D17*E17)
B18: DCP / Deliverables Mastering | F18: =IF(C18="","",C18*D18*E18)
B19: Final Hard Drives / Archiving | F19: =IF(C19="","",C19*D19*E19)
B20: TOTAL — Post Production | C20: =SUM(F5:F19) -> 0 | F20: =SUM(F5:F19) -> 0
B22: NOTE: Enter Rate, Units, and Days for each line item. Total calculates automatically.

Sheet Music
B2: HEARTH · Music
B4: Line Item | C4: Rate ($) | D4: # Units | E4: # Days | F4: Total ($) | G4: Notes
B5: ORIGINAL SCORE
B6: Composer Fee | F6: =IF(C6="","",C6*D6*E6)
B7: Music Recording Session | F7: =IF(C7="","",C7*D7*E7)
B8: LICENSED MUSIC
B9: Licensed Track 1 — Master + Sync | F9: =IF(C9="","",C9*D9*E9)
B10: Licensed Track 2 — Master + Sync | F10: =IF(C10="","",C10*D10*E10)
B11: Licensed Track 3 — Master + Sync | F11: =IF(C11="","",C11*D11*E11)
B12: Music Library Subscription | F12: =IF(C12="","",C12*D12*E12)
B13: TOTAL — Music | C13: =SUM(F5:F12) -> 0 | F13: =SUM(F5:F12) -> 0
B15: NOTE: Enter Rate, Units, and Days for each line item. Total calculates automatically.

Sheet Other
B2: HEARTH · Other
B4: Line Item | C4: Rate ($) | D4: # Units | E4: # Days | F4: Total ($) | G4: Notes
B5: INSURANCE & LEGAL
B6: Production Insurance | F6: =IF(C6="","",C6*D6*E6)
B7: Errors & Omissions (E&O) Insurance | F7: =IF(C7="","",C7*D7*E7)
B8: Legal / Contract Review | F8: =IF(C8="","",C8*D8*E8)
B9: ADMINISTRATION
B10: Accounting / Bookkeeping | F10: =IF(C10="","",C10*D10*E10)
B11: Payroll Processing Fees | F11: =IF(C11="","",C11*D11*E11)
B12: Bank Fees / Wire Transfers | F12: =IF(C12="","",C12*D12*E12)
B13: FESTIVAL & DISTRIBUTION
B14: Festival Submission Fees | F14: =IF(C14="","",C14*D14*E14)
B15: EPK / Press Materials | F15: =IF(C15="","",C15*D15*E15)
B16: Publicity / Screening Costs | F16: =IF(C16="","",C16*D16*E16)
B17: MISCELLANEOUS
B18: Miscellaneous / Unforeseen | F18: =IF(C18="","",C18*D18*E18)
B19: TOTAL — Other | C19: =SUM(F5:F18) -> 0 | F19: =SUM(F5:F18) -> 0
B21: NOTE: Enter Rate, Units, and Days for each line item. Total calculates automatically.
